verusdb/__init__.py
verusdb/client.py
verusdb/embeddings/__init__.py
verusdb/embeddings/openai.py
verusdb/engines/__init__.py
verusdb/engines/polars.py
verusdb/engines/postgresql.py
verusdb/engines/redis.py
verusdb/settings.py
verusdb/utils.py
verusdb-0.0.1.dist-info/LICENSE
verusdb-0.0.1.dist-info/METADATA
verusdb-0.0.1.dist-info/WHEEL
verusdb-0.0.1.dist-info/RECORD
