Metadata-Version: 2.1
Name: verusdb
Version: 0.0.1
Summary: 
Author: Roger Naranjo
Author-email: rogernaranjo@gmail.com
Requires-Python: >=3.8,<4.0
Classifier: Programming Language :: Python :: 3
Classifier: Programming Language :: Python :: 3.8
Classifier: Programming Language :: Python :: 3.9
Classifier: Programming Language :: Python :: 3.10
Classifier: Programming Language :: Python :: 3.11
Requires-Dist: numpy (>=1.24.3,<2.0.0)
Requires-Dist: openai (>=0.27.8,<0.28.0)
Requires-Dist: polars (>=0.18.2,<0.19.0)
Requires-Dist: psycopg2 (>=2.9.6,<3.0.0)
Requires-Dist: redis (>=4.5.5,<5.0.0)
